{
  "bundleId" : "com.knollsoft.Hookshot",
  "defaults" : {
    "SUEnableAutomaticChecks" : {
      "bool" : false
    },
    "adjacentResizeScreenEdge" : {
      "int" : 0
    },
    "adjacentResizing" : {
      "int" : 1
    },
    "allowAnyShortcut" : {
      "bool" : true
    },
    "almostMaximizeHeight" : {
      "float" : 0
    },
    "almostMaximizeWidth" : {
      "float" : 0
    },
    "altThirdCycle" : {
      "int" : 0
    },
    "alternateDefaultShortcuts" : {
      "bool" : false
    },
    "alternateGestureShortcuts" : {
      "bool" : false
    },
    "alwaysAccountForStage" : {
      "int" : 0
    },
    "alwaysAllowThrow" : {
      "int" : 0
    },
    "analogAdjacentResizing" : {
      "int" : 0
    },
    "appLayoutsHideOtherApps" : {
      "int" : 0
    },
    "appSpecs" : {
      "string" : "[{\"children\":[{\"otherAppOperation\":1,\"id\":392,\"bundleId\":\"~global\",\"loc\":0,\"windowAction\":20},{\"otherAppOperation\":1,\"id\":409,\"bundleId\":\"~global\",\"loc\":0,\"windowAction\":22},{\"otherAppOperation\":1,\"id\":426,\"bundleId\":\"~global\",\"loc\":0,\"windowAction\":24}],\"name\":\"1\\\/1\\\/1 Left\",\"shortcut\":{\"keyCode\":12,\"modifierFlags\":786432},\"loc\":0,\"id\":375,\"isGroup\":true,\"otherAppOperation\":1},{\"loc\":0,\"otherAppOperation\":1,\"shortcut\":{\"keyCode\":14,\"modifierFlags\":786432},\"id\":19,\"children\":[{\"otherAppOperation\":1,\"id\":70,\"children\":[{\"loc\":3,\"bundleId\":\"~global\",\"id\":356,\"otherAppOperation\":1},{\"loc\":0,\"otherAppOperation\":1,\"id\":361}],\"loc\":0,\"bundleId\":\"~global\",\"windowAction\":24},{\"otherAppOperation\":1,\"id\":36,\"children\":[{\"bundleId\":\"~global\",\"otherAppOperation\":1,\"id\":357,\"loc\":0},{\"loc\":4,\"id\":360,\"otherAppOperation\":1}],\"loc\":0,\"bundleId\":\"~global\",\"windowAction\":20},{\"children\":[{\"id\":358,\"loc\":4,\"bundleId\":\"~global\",\"otherAppOperation\":1},{\"id\":362,\"loc\":3,\"otherAppOperation\":1}],\"windowAction\":22,\"bundleId\":\"~global\",\"loc\":0,\"id\":53,\"otherAppOperation\":1}],\"isGroup\":true,\"name\":\"1\\\/1\\\/1 Right\",\"bringToFront\":true},{\"loc\":0,\"otherAppOperation\":1,\"shortcut\":{\"modifierFlags\":786432,\"keyCode\":13},\"id\":121,\"children\":[{\"x\":\"279\",\"displayFrame\":[[-867,1169],[3440,1440]],\"w\":\"2294\",\"loc\":9,\"y\":\"1169\",\"bundleId\":\"~global\",\"otherAppOperation\":1,\"id\":105,\"windowAction\":21,\"children\":[{\"id\":159,\"w\":\"0.33\",\"otherAppOperation\":1,\"h\":\"1\",\"bundleId\":\"~global\",\"loc\":3}],\"h\":\"1409\",\"display\":0},{\"id\":140,\"otherAppOperation\":1,\"windowAction\":24,\"bundleId\":\"~global\",\"loc\":0,\"children\":[{\"w\":\"0.67\",\"loc\":4,\"id\":160,\"otherAppOperation\":1,\"h\":\"1\",\"bundleId\":\"~global\"}]}],\"isGroup\":true,\"name\":\"2\\\/1\"},{\"loc\":0,\"otherAppOperation\":1,\"shortcut\":{\"keyCode\":0,\"modifierFlags\":786432},\"id\":190,\"isGroup\":true,\"children\":[{\"children\":[{\"otherAppOperation\":1,\"bundleId\":\"~global\",\"h\":\"0.5\",\"id\":193,\"loc\":2}],\"display\":-4,\"title\":\"PUrbFdKyJKZiGlNPwzueWdGkJGt7DuJwpiMZC0Lk\",\"displayFrame\":[[-1440,-1027],[1440,2560]],\"windowAction\":11,\"otherAppOperation\":1,\"h\":\"1259\",\"w\":\"1432\",\"bundleId\":\"~global\",\"id\":166,\"x\":\"-1436\",\"displayID\":\"98E74029-98D3-4332-8F45-436D5BF783E8\",\"y\":\"240\",\"loc\":9,\"displayName\":\"HP Z27n\"},{\"children\":[{\"otherAppOperation\":1,\"bundleId\":\"~global\",\"h\":\"0.5\",\"id\":194,\"loc\":1}],\"display\":-4,\"title\":\"UseJWEjh1rQ4yPNFZrCmrfMbR621TmzrXxMsAIlUoTWOwPlUUnDN28IxXVhEv0hpV7+u74+J0eI7Ken0IB+edWM=\",\"displayFrame\":[[-1440,-1027],[1440,2560]],\"windowAction\":10,\"otherAppOperation\":1,\"h\":\"1259\",\"w\":\"1432\",\"bundleId\":\"~global\",\"id\":168,\"x\":\"-1436\",\"displayID\":\"98E74029-98D3-4332-8F45-436D5BF783E8\",\"y\":\"-1023\",\"loc\":9,\"displayName\":\"HP Z27n\"}],\"name\":\"Top Bottom\"},{\"loc\":0,\"applyOtherAppOperation\":true,\"otherAppOperation\":1,\"shortcut\":{\"modifierFlags\":786432,\"keyCode\":34},\"id\":196,\"launchApps\":true,\"isGroup\":true,\"children\":[{\"loc\":0,\"otherAppOperation\":1,\"bundleId\":\"com.google.Chrome\",\"titleMatching\":1,\"id\":209,\"windowAction\":29,\"display\":-1},{\"x\":\"2306\",\"windowAction\":24,\"h\":\"1362\",\"y\":\"43\",\"otherAppOperation\":1,\"displayFrame\":[[0,0],[3440,1440]],\"titleMatching\":1,\"w\":\"1129\",\"bundleId\":\"com.googlecode.iterm2\",\"display\":0,\"id\":197,\"title\":\"rreiYEyYZMg8NXn+ELUO6XGcoYiYzMrXlYqB+w==\",\"loc\":9},{\"x\":\"4\",\"windowAction\":21,\"h\":\"1362\",\"y\":\"43\",\"otherAppOperation\":1,\"displayFrame\":[[0,0],[3440,1440]],\"titleMatching\":1,\"w\":\"2299\",\"bundleId\":\"com.microsoft.VSCode\",\"display\":0,\"id\":198,\"title\":\"3WuydJF9R6zFXG2uFyahjpeK+KcB0C2iagDZnUCKOefDRQMJYPj964MFdonq0SMRSypqr9Qa4w==\",\"loc\":9}],\"name\":\"Coding + Term\",\"bringToFront\":true},{\"loc\":0,\"otherAppOperation\":1,\"shortcut\":{\"modifierFlags\":786432,\"keyCode\":38},\"id\":218,\"isGroup\":true,\"children\":[{\"id\":231,\"display\":-1,\"loc\":0,\"windowAction\":21,\"bundleId\":\"com.google.Chrome\",\"otherAppOperation\":1},{\"x\":\"2292\",\"displayFrame\":[[0,0],[3440,1440]],\"w\":\"1129\",\"loc\":9,\"y\":\"47\",\"bundleId\":\"com.google.Chrome.app.objbpcoehdclpkicmejghhppkkdemhok\",\"otherAppOperation\":1,\"id\":250,\"windowAction\":24,\"h\":\"1362\",\"display\":0}],\"name\":\"Documentation\",\"bringToFront\":true},{\"loc\":0,\"otherAppOperation\":1,\"shortcut\":{\"modifierFlags\":786432,\"keyCode\":43},\"id\":305,\"launchApps\":true,\"isGroup\":true,\"children\":[{\"loc\":0,\"otherAppOperation\":1,\"w\":\"0.6\",\"bundleId\":\"com.microsoft.teams2\",\"id\":324,\"windowAction\":11,\"children\":[{\"loc\":0,\"otherAppOperation\":1,\"w\":\"0.6\",\"bundleId\":\"com.microsoft.teams2\",\"id\":327,\"h\":\"0.6\",\"display\":-1}],\"h\":\"0.6\",\"display\":1}],\"name\":\"Teams\",\"applyToAll\":true,\"bringToFront\":true},{\"loc\":0,\"otherAppOperation\":1,\"shortcut\":{\"modifierFlags\":786432,\"keyCode\":37},\"id\":339,\"launchApps\":true,\"children\":[{\"windowAction\":19,\"otherAppOperation\":1,\"loc\":0,\"id\":354,\"bundleId\":\"com.spotify.client\",\"children\":[{\"otherAppOperation\":1,\"id\":355,\"h\":\"1\",\"w\":\"0.33\",\"loc\":4,\"bundleId\":\"com.spotify.client\"}]}],\"isGroup\":true,\"name\":\"Spotify\"},{\"loc\":0,\"otherAppOperation\":1,\"shortcut\":{\"keyCode\":19,\"modifierFlags\":786432},\"id\":477,\"isGroup\":true,\"children\":[{\"bundleId\":\"~global\",\"loc\":0,\"windowAction\":0,\"id\":498,\"otherAppOperation\":1},{\"bundleId\":\"~global\",\"titleMatching\":1,\"loc\":0,\"windowAction\":1,\"id\":519,\"otherAppOperation\":1}],\"name\":\"Halves\"}]"
    },
    "applyGapToEdges" : {
      "int" : 0
    },
    "attemptMatchOnNextPrevDisplay" : {
      "int" : 0
    },
    "autoRestartOnWake" : {
      "int" : 0
    },
    "cascadeHeight" : {
      "int" : 0
    },
    "cascadeWidth" : {
      "int" : 0
    },
    "centerFixedDimensions" : {
      "int" : 0
    },
    "centerHalfCycles" : {
      "int" : 0
    },
    "centeredDirectionalMove" : {
      "int" : 0
    },
    "checkAnimationUnsnap" : {
      "int" : 0
    },
    "checkFullScreen" : {
      "int" : 0
    },
    "clickMoveMouseButton" : {
      "int" : 0
    },
    "clickResizeMouseButton" : {
      "int" : 0
    },
    "contextMenuModifiers" : {
      "int" : 786432
    },
    "contextMenuShortcut" : {
      "string" : "{\"keyCode\":53,\"modifierFlags\":786432}"
    },
    "cornerSnapAreaSize" : {
      "float" : 20
    },
    "cursorGestures" : {
      "int" : 0
    },
    "curtainChangeSize" : {
      "int" : 0
    },
    "cycleSizesIsChanged" : {
      "bool" : false
    },
    "defaultLayoutExclusion" : {
      "int" : 98318
    },
    "disabledApps" : {
      "string" : "[\"com.knollsoft.Hookshot\"]"
    },
    "dockDetection" : {
      "int" : 0
    },
    "dockSizePollSeconds" : {
      "double" : 0
    },
    "doubleClickTitleBar" : {
      "int" : 0
    },
    "doubleClickTitleBarIgnoredApps" : {

    },
    "doubleClickTitleBarRestore" : {
      "int" : 0
    },
    "dragFromStage" : {
      "int" : 0
    },
    "dropPaneLocation" : {
      "int" : 8
    },
    "dropPaneModifier" : {
      "int" : 0
    },
    "enhancedUI" : {
      "int" : 1
    },
    "fillLeftRightVersion" : {
      "int" : 2
    },
    "focusRefreshBehavior" : {
      "int" : 0
    },
    "footprintAlpha" : {
      "float" : 0.3
    },
    "footprintAnimationDurationMultiplier" : {
      "float" : 0
    },
    "footprintBorderWidth" : {
      "float" : 2
    },
    "footprintColor" : {

    },
    "footprintFade" : {
      "int" : 0
    },
    "gapSize" : {
      "double" : 4
    },
    "gestures" : {

    },
    "hapticFeedbackOnSnap" : {
      "int" : 0
    },
    "helperRelaunch" : {
      "int" : 1
    },
    "hideMenubarIcon" : {
      "bool" : false
    },
    "hideReticleRectangles" : {
      "bool" : false
    },
    "hookshotStatusIcon" : {
      "int" : 2
    },
    "iCloudSync" : {
      "int" : 1
    },
    "iconDrawing" : {
      "int" : 3
    },
    "ignoreBehavior" : {
      "int" : 0
    },
    "ignoreDock" : {
      "int" : 0
    },
    "ignoredSnapAreas" : {
      "int" : 0
    },
    "keyboardShortcutsEnabled" : {
      "int" : 0
    },
    "landscapeSnapAreas" : {

    },
    "launchOnLogin" : {
      "bool" : true
    },
    "layoutSaveType" : {
      "int" : 2
    },
    "lockstepResizeOnScreenEdge" : {
      "int" : 0
    },
    "longReticleSpec" : {

    },
    "longshotDist" : {
      "float" : 200
    },
    "mainReticleSpec" : {

    },
    "manualSpecs" : {
      "string" : "[]"
    },
    "maximizeAcrossDisplays" : {
      "int" : 0
    },
    "menuActionVisibility" : {
      "string" : "{\"134\":{\"shown\":true},\"29\":{\"shown\":false},\"3\":{\"shown\":false},\"133\":{\"shown\":true}}"
    },
    "menuAppSpecVisibility" : {

    },
    "menuCategoryVisibility" : {
      "string" : "{\"3\":{\"shown\":false,\"shownAsSubmenu\":false},\"5\":{\"shown\":false,\"shownAsSubmenu\":false},\"13\":{\"shown\":false,\"shownAsSubmenu\":false},\"11\":{\"shown\":false,\"shownAsSubmenu\":false},\"14\":{\"shown\":false,\"shownAsSubmenu\":true},\"19\":{\"shown\":false,\"shownAsSubmenu\":true}}"
    },
    "menuCustomSpecVisibility" : {

    },
    "minimumWindowHeight" : {
      "float" : 0.1
    },
    "minimumWindowWidth" : {
      "float" : 0.1
    },
    "missionControlDragging" : {
      "int" : 0
    },
    "missionControlDraggingAllowedOffscreenDistance" : {
      "float" : 25
    },
    "missionControlDraggingDisallowedDuration" : {
      "int" : 250
    },
    "mouseThrowSyntheticDrag" : {
      "int" : 0
    },
    "moveCursorAcrossDisplays" : {
      "int" : 0
    },
    "moveResizeEventThrottling" : {
      "int" : 0
    },
    "moveSpecsWhenDisplayMoves" : {
      "int" : 0
    },
    "multiWindowAllDisplays" : {
      "int" : 0
    },
    "multiWindowRespectsIgnore" : {
      "int" : 0
    },
    "nextPrevSpaceFrontWindowDelay" : {
      "int" : 300
    },
    "nsClickListen" : {
      "int" : 0
    },
    "nsEventListen" : {
      "int" : 0
    },
    "nudgeDistance" : {
      "float" : 20
    },
    "obtainWindowOnClick" : {
      "int" : 0
    },
    "openWindowLayoutExclusion" : {
      "int" : 128
    },
    "performRepeatOnThrow" : {
      "int" : 0
    },
    "portraitLeftRightIsTopBottom" : {
      "int" : 0
    },
    "portraitSnapAreas" : {

    },
    "preciseScrollTriggerIncrements" : {
      "float" : 10
    },
    "quickActionMinDist" : {
      "float" : 10
    },
    "quickActionTimeout" : {
      "double" : 1
    },
    "quickActions" : {
      "int" : 0
    },
    "relaunchOpensMenu" : {
      "bool" : false
    },
    "repeatedMaximizeMode" : {
      "int" : 4
    },
    "repeatedMaximizeRestores" : {
      "int" : 0
    },
    "resizeFromNearestCorner" : {
      "int" : 0
    },
    "resizeOnDirectionalMove" : {
      "bool" : false
    },
    "restToOneTouches" : {
      "int" : 0
    },
    "restartOnWakeDelay" : {
      "float" : 0
    },
    "reticle" : {
      "int" : 2
    },
    "reticleColor" : {
      "string" : "{\"alpha\":0.5,\"red\":0.8,\"green\":0.3,\"blue\":0.2}"
    },
    "reticleDisplayMinDist" : {
      "float" : 0
    },
    "reticleMouseButton" : {
      "int" : 0
    },
    "reticleSize" : {
      "int" : 12
    },
    "revealDesktopWidth" : {
      "float" : 200
    },
    "safeAreaSize" : {
      "int" : 35
    },
    "saveLayoutShortcut" : {

    },
    "screenEdgeGapBottom" : {
      "float" : 0
    },
    "screenEdgeGapLeft" : {
      "float" : 0
    },
    "screenEdgeGapRight" : {
      "float" : 0
    },
    "screenEdgeGapTop" : {
      "float" : 0
    },
    "screenEdgeGapTopNotch" : {
      "float" : 0
    },
    "screenEdgeGapsOnMainScreenOnly" : {
      "bool" : false
    },
    "screensOrderedByX" : {
      "int" : 0
    },
    "scrollEdgePauseDistance" : {
      "float" : 60
    },
    "scrollEdgePauseSpeed" : {
      "float" : 20
    },
    "scrollTriggerIncrements" : {
      "float" : 0.1
    },
    "selectedCycleSizes" : {
      "int" : 0
    },
    "shortEdgeSnapAreaSize" : {
      "float" : 145
    },
    "showAllActionsInMenu" : {
      "int" : 0
    },
    "sixthsSnapArea" : {
      "int" : 0
    },
    "sizeOffset" : {
      "float" : 30
    },
    "smallerLargerOffsetV2" : {
      "float" : 20
    },
    "snapEdgeMarginBottom" : {
      "float" : 5
    },
    "snapEdgeMarginLeft" : {
      "float" : 5
    },
    "snapEdgeMarginRight" : {
      "float" : 5
    },
    "snapEdgeMarginTop" : {
      "float" : 5
    },
    "snapModifiers" : {
      "int" : 0
    },
    "snapPanelActions" : {
      "string" : "[{\"windowAction\":134},{\"windowAction\":0},{\"manualSpecId\":375,\"windowAction\":36},{\"manualSpecId\":121,\"windowAction\":36},{\"manualSpecId\":19,\"windowAction\":36},{\"windowAction\":1},{\"windowAction\":107},{\"windowAction\":133}]"
    },
    "specifiedHeight" : {
      "float" : 1050
    },
    "specifiedWidth" : {
      "float" : 1680
    },
    "stageSize" : {
      "float" : 190
    },
    "stashAnimation" : {
      "int" : 0
    },
    "stashAppIconColorTabs" : {
      "int" : 0
    },
    "stashClearScreenEdge" : {
      "int" : 0
    },
    "stashClearedByOtherActions" : {
      "int" : 0
    },
    "stashCursorBoxWidth" : {
      "float" : 1
    },
    "stashEnabled" : {
      "int" : 0
    },
    "stashHideCursorWindow" : {
      "int" : 0
    },
    "stashHideTime" : {
      "double" : 0.3
    },
    "stashHideUsingMod" : {
      "int" : 0
    },
    "stashInMenu" : {
      "int" : 0
    },
    "stashMultipleStagger" : {
      "int" : 0
    },
    "stashShowTime" : {
      "double" : 0.3
    },
    "stashShowUsingMod" : {
      "int" : 0
    },
    "stashTabs" : {
      "int" : 0
    },
    "stashToCorner" : {
      "int" : 0
    },
    "stashVisibleWidth" : {
      "float" : 1
    },
    "subsequentExecutionMode" : {
      "int" : 0
    },
    "systemWideMouseDown" : {
      "int" : 0
    },
    "systemWideMouseDownApps" : {

    },
    "throwFrontmost" : {
      "int" : 0
    },
    "throwScrollResize" : {
      "int" : 0
    },
    "tidyGranularity" : {
      "int" : 1
    },
    "todo" : {
      "int" : 1
    },
    "todoApplication" : {
      "string" : "com.google.Chrome"
    },
    "todoMode" : {
      "bool" : false
    },
    "todoSide" : {
      "int" : 1
    },
    "todoSidebarWidth" : {
      "double" : 25
    },
    "togggleTodoShortcut" : {
      "string" : "{\"modifierFlags\":786432,\"keyCode\":35}"
    },
    "toggleShortcutsShortcut" : {

    },
    "traverseSingleScreen" : {
      "int" : 0
    },
    "unhideStashToOriginal" : {
      "int" : 0
    },
    "unhideStashedWhenFrontmost" : {
      "int" : 0
    },
    "unifiedDisplaySpacesBehavior" : {
      "int" : 0
    },
    "unsnapRestore" : {
      "int" : 0
    },
    "unstashAllToFront" : {
      "int" : 0
    },
    "unstashOnTerminate" : {
      "int" : 0
    },
    "winDownDefaultAction" : {
      "int" : 0
    },
    "winModFlags" : {
      "int" : 0
    },
    "windowPollSeconds" : {
      "double" : 0.5
    },
    "windowSnapping" : {
      "int" : 1
    },
    "windowStopVelocity" : {
      "float" : 3
    },
    "windowThrowIgnoresWidgets" : {
      "int" : 0
    },
    "windowToFront" : {
      "int" : 0
    }
  },
  "shortcuts" : {

  },
  "timestamp" : 800526538.180492,
  "version" : "223"
}